MANIFEST.in
README.rst
rsvpcron
setup.py
rsvpmeetup/__init__.py
rsvpmeetup/api.py
rsvpmeetup/errors.py
rsvpmeetup/helper.py
rsvpmeetup/path.txt
rsvpmeetup.egg-info/PKG-INFO
rsvpmeetup.egg-info/SOURCES.txt
rsvpmeetup.egg-info/dependency_links.txt
rsvpmeetup.egg-info/not-zip-safe
rsvpmeetup.egg-info/requires.txt
rsvpmeetup.egg-info/top_level.txt
rsvpmeetup/headers/initial_header.json
rsvpmeetup/headers/login_header.json
rsvpmeetup/headers/rsvp_header.json
rsvpmeetup/headers/standard_header.json