Metadata-Version: 1.0
Name: rsvpmeetup
Version: 0.2
Summary: A Module to Automatically rsvp yes to events in configured events for meetup.com
Home-page: https://github.com/vishwesh-D-kumar/MeetupRSVP
Author: Vishwesh Kumar
Author-email: vishwesh18119@iiitd.ac.in
License: MIT
Platform: UNKNOWN
